billing_audit/__init__.py
billing_audit/database/__init__.py
billing_audit/database/_celery_task_db_wrapper.py
billing_audit-1.0.1.dist-info/METADATA
billing_audit-1.0.1.dist-info/WHEEL
billing_audit-1.0.1.dist-info/top_level.txt
billing_audit-1.0.1.dist-info/RECORD
