Metadata-Version: 2.1
Name: billing-audit
Version: 1.0.1
Summary: Billing audit utils
Home-page: https://git.paas.vn/devteam/billing/audit-services/audit-utils
Author: vuonglv
Author-email: vuonglv@vccloud.vn
License: UNKNOWN
Platform: UNKNOWN
Classifier: Programming Language :: Python :: 3
Classifier: Operating System :: OS Independent
Requires-Python: >=3.6
